MANIFEST.in
README.md
setup.cfg
setup.py
clustergrammer_glidget/__init__.py
clustergrammer_glidget/_version.py
clustergrammer_glidget/example.py
clustergrammer_glidget.egg-info/PKG-INFO
clustergrammer_glidget.egg-info/SOURCES.txt
clustergrammer_glidget.egg-info/dependency_links.txt
clustergrammer_glidget.egg-info/not-zip-safe
clustergrammer_glidget.egg-info/requires.txt
clustergrammer_glidget.egg-info/top_level.txt
clustergrammer_glidget/clustergrammer/__init__.py
clustergrammer_glidget/clustergrammer/calc_clust.py
clustergrammer_glidget/clustergrammer/cat_pval.py
clustergrammer_glidget/clustergrammer/categories.py
clustergrammer_glidget/clustergrammer/data_formats.py
clustergrammer_glidget/clustergrammer/downsample_fun.py
clustergrammer_glidget/clustergrammer/enrichr_functions.py
clustergrammer_glidget/clustergrammer/export_data.py
clustergrammer_glidget/clustergrammer/iframe_web_app.py
clustergrammer_glidget/clustergrammer/initialize_net.py
clustergrammer_glidget/clustergrammer/load_data.py
clustergrammer_glidget/clustergrammer/load_vect_post.py
clustergrammer_glidget/clustergrammer/make_clust_fun.py
clustergrammer_glidget/clustergrammer/make_sim_mat.py
clustergrammer_glidget/clustergrammer/make_unique_labels.py
clustergrammer_glidget/clustergrammer/make_views.py
clustergrammer_glidget/clustergrammer/make_viz.py
clustergrammer_glidget/clustergrammer/normalize_fun.py
clustergrammer_glidget/clustergrammer/proc_df_labels.py
clustergrammer_glidget/clustergrammer/run_filter.py
clustergrammer_glidget/static/extension.js
clustergrammer_glidget/static/f2c72c12e473db657b6f061871c24289.png
clustergrammer_glidget/static/index.js
clustergrammer_glidget/static/index.js.map